paga_business_client/__init__.py
paga_business_client/_version.py
paga_business_client/apibase.py
paga_business_client/business_client_core.py
paga_business_client/onboard_merchant.py
paga_business_client/version.py
paga_business_client-0.0.5.dist-info/AUTHORS.rst
paga_business_client-0.0.5.dist-info/LICENSE
paga_business_client-0.0.5.dist-info/METADATA
paga_business_client-0.0.5.dist-info/WHEEL
paga_business_client-0.0.5.dist-info/top_level.txt
paga_business_client-0.0.5.dist-info/RECORD
