Metadata-Version: 2.1
Name: paga-business-client
Version: 0.0.5
Summary: Paga Business CLient
Home-page: https://github.com/pagadevcomm/pagadevcomm/paga_business_library
Author: Paga Developer Community
Author-email: devcomm@paga.com
License: MIT
Project-URL: Changelog, https://github.com/pagadevcomm/pagadevcomm/paga_business_library/blob/master/CHANGELOG.rst
Project-URL: Issue Tracker, https://github.com/pagadevcomm/pagadevcomm/paga_business_library/issues
Platform: UNKNOWN
Classifier: Development Status :: 5 - Production/Stable
Classifier: Intended Audience :: Developers
Classifier: License :: OSI Approved :: MIT License
Classifier: Operating System :: Unix
Classifier: Operating System :: POSIX
Classifier: Operating System :: Microsoft :: Windows
Classifier: Programming Language :: Python
Classifier: Programming Language :: Python :: 2.7
Classifier: Programming Language :: Python :: 3
Classifier: Programming Language :: Python :: 3.5
Classifier: Programming Language :: Python :: 3.6
Classifier: Programming Language :: Python :: 3.7
Classifier: Programming Language :: Python :: 3.8
Classifier: Programming Language :: Python :: Implementation :: CPython
Classifier: Programming Language :: Python :: Implementation :: PyPy
Classifier: Topic :: Utilities
Requires-Python: >=2.7, !=3.0.*, !=3.1.*, !=3.2.*, !=3.3.*, !=3.4.*
